easel/__init__.py
easel/cli.py
easel/main/__init__.py
easel/main/assets/static/css/fonts.css
easel/main/assets/static/css/main.css
easel/main/assets/static/css/markdown.css
easel/main/assets/static/css/reset.css
easel/main/assets/static/fonts/Fira_Code_v5.2/README.txt
easel/main/assets/static/fonts/Fira_Code_v5.2/fira_code.css
easel/main/assets/static/fonts/Fira_Code_v5.2/specimen.html
easel/main/assets/static/fonts/Fira_Code_v5.2/ttf/FiraCode-Bold.ttf
easel/main/assets/static/fonts/Fira_Code_v5.2/ttf/FiraCode-Light.ttf
easel/main/assets/static/fonts/Fira_Code_v5.2/ttf/FiraCode-Medium.ttf
easel/main/assets/static/fonts/Fira_Code_v5.2/ttf/FiraCode-Regular.ttf
easel/main/assets/static/fonts/Fira_Code_v5.2/ttf/FiraCode-Retina.ttf
easel/main/assets/static/fonts/Fira_Code_v5.2/ttf/FiraCode-SemiBold.ttf
easel/main/assets/static/fonts/Fira_Code_v5.2/variable_ttf/FiraCode-VF.ttf
easel/main/assets/static/fonts/Fira_Code_v5.2/woff/FiraCode-Bold.woff
easel/main/assets/static/fonts/Fira_Code_v5.2/woff/FiraCode-Light.woff
easel/main/assets/static/fonts/Fira_Code_v5.2/woff/FiraCode-Medium.woff
easel/main/assets/static/fonts/Fira_Code_v5.2/woff/FiraCode-Regular.woff
easel/main/assets/static/fonts/Fira_Code_v5.2/woff/FiraCode-SemiBold.woff
easel/main/assets/static/fonts/Fira_Code_v5.2/woff/FiraCode-VF.woff
easel/main/assets/static/fonts/Fira_Code_v5.2/woff2/FiraCode-Bold.woff2
easel/main/assets/static/fonts/Fira_Code_v5.2/woff2/FiraCode-Light.woff2
easel/main/assets/static/fonts/Fira_Code_v5.2/woff2/FiraCode-Medium.woff2
easel/main/assets/static/fonts/Fira_Code_v5.2/woff2/FiraCode-Regular.woff2
easel/main/assets/static/fonts/Fira_Code_v5.2/woff2/FiraCode-SemiBold.woff2
easel/main/assets/static/fonts/Fira_Code_v5.2/woff2/FiraCode-VF.woff2
easel/main/assets/static/fonts/Fira_Code_v5.2.zip
easel/main/assets/static/fonts/PT_Sans/OFL.txt
easel/main/assets/static/fonts/PT_Sans/PTSans-Bold.ttf
easel/main/assets/static/fonts/PT_Sans/PTSans-BoldItalic.ttf
easel-1.0.0.dist-info/entry_points.txt
easel-1.0.0.dist-info/LICENSE.txt
easel-1.0.0.dist-info/WHEEL
easel-1.0.0.dist-info/METADATA
easel-1.0.0.dist-info/RECORD
