Metadata-Version: 2.1
Name: easel
Version: 1.0.0
Summary: Showcasing work for the lazy. Built on Flask, YAML, Markdown and directories.
Home-page: https://github.com/tnahs/easel
License: MIT
Keywords: Flask,YAML,Markdown,Portfolio
Author: Shant Ergenian
Author-email: shant.ergenian@gmail.com
Maintainer: Shant Ergenian
Maintainer-email: shant.ergenian@gmail.com
Requires-Python: >=3.8,<4.0
Classifier: License :: OSI Approved :: MIT License
Classifier: Programming Language :: Python :: 3
Classifier: Programming Language :: Python :: 3.8
Requires-Dist: flask (>=1.1.2,<2.0.0)
Requires-Dist: markdown (>=3.2.2,<4.0.0)
Requires-Dist: pymdown-extensions (>=7.1,<8.0)
Requires-Dist: pyyaml (>=5.3.1,<6.0.0)
Project-URL: Repository, https://github.com/tnahs/easel
